oa_missionaries_and_cannibals.py
oa_missionaries_and_cannibals-0.0.8.dist-info/LICENSE
oa_missionaries_and_cannibals-0.0.8.dist-info/METADATA
oa_missionaries_and_cannibals-0.0.8.dist-info/WHEEL
oa_missionaries_and_cannibals-0.0.8.dist-info/top_level.txt
oa_missionaries_and_cannibals-0.0.8.dist-info/RECORD
