Metadata-Version: 2.1
Name: oa-missionaries-and-cannibals
Version: 0.0.8
Summary: Missionaries and Cannibals using BFS and State Space Search
Author: The OA
Classifier: Programming Language :: Python :: 3
Classifier: License :: OSI Approved :: MIT License
Classifier: Operating System :: OS Independent
Requires-Python: >=3.6
License-File: LICENSE
